{
  "_class": "symbolInstance",
  "do_objectID": "B324C12F-0B3A-4501-88A6-936743D4FA5F",
  "exportOptions": {
    "_class": "exportOptions",
    "exportFormats": [
    ],
    "includedLayerIds": [
    ],
    "layerOptions": 0,
    "shouldTrim": false
  },
  "frame": {
    "_class": "rect",
    "constrainProportions": false,
    "height": 42,
    "width": 142,
    "x": 8,
    "y": 338
  },
  "horizontalSpacing": 0,
  "isFlippedHorizontal": false,
  "isFlippedVertical": false,
  "isLocked": false,
  "isVisible": true,
  "layerListExpandedType": 0,
  "masterInfluenceEdgeMaxXPadding": 1,
  "masterInfluenceEdgeMaxYPadding": 2,
  "masterInfluenceEdgeMinXPadding": 1,
  "masterInfluenceEdgeMinYPadding": 1,
  "name": "castelo_dos_hamburguers",
  "nameIsFixed": true,
  "originalObjectID": "143EA516-F626-4EC8-9467-25B155696855",
  "overrides": {
    "CF5ECDCD-6A4F-404D-A450-B1DC56CDA924": "Castelo ..."
  },
  "resizingConstraint": 63,
  "resizingType": 0,
  "rotation": 0,
  "shouldBreakMaskChain": false,
  "style": {
    "_class": "style",
    "endDecorationType": 0,
    "miterLimit": 10,
    "startDecorationType": 0
  },
  "symbolID": "939B242D-4F9D-4FF7-9B8A-780576DFC4D4",
  "verticalSpacing": 0
}