{
  "_class": "oval",
  "booleanOperation": 0,
  "do_objectID": "578A4CA1-1B23-4EC2-A95B-11F13BF4AE14",
  "edited": true,
  "exportOptions": {
    "_class": "exportOptions",
    "exportFormats": [
    ],
    "includedLayerIds": [
    ],
    "layerOptions": 0,
    "shouldTrim": false
  },
  "frame": {
    "_class": "rect",
    "constrainProportions": false,
    "height": 3,
    "width": 3.729205453588858,
    "x": 0,
    "y": 3.153064044762699
  },
  "isFlippedHorizontal": false,
  "isFlippedVertical": false,
  "isLocked": false,
  "isVisible": true,
  "layerListExpandedType": 0,
  "name": "Oval 5",
  "nameIsFixed": false,
  "path": {
    "_class": "path",
    "isClosed": true,
    "pointRadiusBehaviour": 1,
    "points": [
      {
        "_class": "curvePoint",
        "cornerRadius": 0,
        "curveFrom": "{0.77614237490000004, 1}",
        "curveMode": 2,
        "curveTo": "{0.22385762510000001, 1}",
        "hasCurveFrom": true,
        "hasCurveTo": true,
        "point": "{0.5, 1}"
      },
      {
        "_class": "curvePoint",
        "cornerRadius": 0,
        "curveFrom": "{1, 0.22385762510000001}",
        "curveMode": 2,
        "curveTo": "{1, 0.77614237490000026}",
        "hasCurveFrom": true,
        "hasCurveTo": true,
        "point": "{1, 0.49999999999999994}"
      },
      {
        "_class": "curvePoint",
        "cornerRadius": 0,
        "curveFrom": "{0.1060813755258323, 4.8241118258681772e-17}",
        "curveMode": 2,
        "curveTo": "{0.8939186244741677, 0}",
        "hasCurveFrom": true,
        "hasCurveTo": true,
        "point": "{0.5, 0}"
      },
      {
        "_class": "curvePoint",
        "cornerRadius": 0,
        "curveFrom": "{0, 0.77614237490000026}",
        "curveMode": 2,
        "curveTo": "{0, 0.22385762510000001}",
        "hasCurveFrom": true,
        "hasCurveTo": true,
        "point": "{0, 0.49999999999999994}"
      }
    ]
  },
  "resizingConstraint": 63,
  "resizingType": 0,
  "rotation": 0,
  "shouldBreakMaskChain": false
}